<?xml version="1.0" encoding="utf-8" ?>
<dwsync>
<file name="index.htm" server="F:/wamp/www/" local="130940159560000000" remote="130940159560000000" Dst="0" />
<file name="thread_activity.php" server="F:/wamp/www/" local="130940159560000000" remote="130940159560000000" Dst="0" />
<file name="thread_album.php" server="F:/wamp/www/" local="130940159560000000" remote="130940159560000000" Dst="0" />
<file name="thread_debate.php" server="F:/wamp/www/" local="130940159560000000" remote="130940159560000000" Dst="0" />
<file name="thread_pay.php" server="F:/wamp/www/" local="130940159560000000" remote="130940159560000000" Dst="0" />
<file name="thread_poll.php" server="F:/wamp/www/" local="130940159560000000" remote="130940159560000000" Dst="0" />
<file name="thread_printable.php" server="F:/wamp/www/" local="130940159560000000" remote="130940159560000000" Dst="0" />
<file name="thread_reward.php" server="F:/wamp/www/" local="130940159560000000" remote="130940159560000000" Dst="0" />
<file name="thread_trade.php" server="F:/wamp/www/" local="130940159560000000" remote="130940159560000000" Dst="0" />
</dwsync>