<?xml version="1.0" encoding="utf-8" ?>
<dwsync>
<file name="av.gif" server="F:/wamp/www/" local="130940159560000000" remote="130940159560000000" Dst="0" />
<file name="binary.gif" server="F:/wamp/www/" local="130940159560000000" remote="130940159560000000" Dst="0" />
<file name="common.gif" server="F:/wamp/www/" local="130940159560000000" remote="130940159560000000" Dst="0" />
<file name="common_new.gif" server="F:/wamp/www/" local="130940159560000000" remote="130940159560000000" Dst="0" />
<file name="file-excel.png" server="F:/wamp/www/" local="130940159560000000" remote="130940159560000000" Dst="0" />
<file name="file-image.png" server="F:/wamp/www/" local="130940159560000000" remote="130940159560000000" Dst="0" />
<file name="file-music.png" server="F:/wamp/www/" local="130940159560000000" remote="130940159560000000" Dst="0" />
<file name="file-video.png" server="F:/wamp/www/" local="130940159560000000" remote="130940159560000000" Dst="0" />
<file name="file-word.png" server="F:/wamp/www/" local="130940159560000000" remote="130940159560000000" Dst="0" />
<file name="file-zip.png" server="F:/wamp/www/" local="130940159560000000" remote="130940159560000000" Dst="0" />
<file name="flash.gif" server="F:/wamp/www/" local="130940159560000000" remote="130940159560000000" Dst="0" />
<file name="html.gif" server="F:/wamp/www/" local="130940159560000000" remote="130940159560000000" Dst="0" />
<file name="image.gif" server="F:/wamp/www/" local="130940159560000000" remote="130940159560000000" Dst="0" />
<file name="image_s.gif" server="F:/wamp/www/" local="130940159560000000" remote="130940159560000000" Dst="0" />
<file name="index.htm" server="F:/wamp/www/" local="130940159560000000" remote="130940159560000000" Dst="0" />
<file name="msoffice.gif" server="F:/wamp/www/" local="130940159560000000" remote="130940159560000000" Dst="0" />
<file name="pdf.gif" server="F:/wamp/www/" local="130940159560000000" remote="130940159560000000" Dst="0" />
<file name="rar.gif" server="F:/wamp/www/" local="130940159560000000" remote="130940159560000000" Dst="0" />
<file name="real.gif" server="F:/wamp/www/" local="130940159560000000" remote="130940159560000000" Dst="0" />
<file name="text.gif" server="F:/wamp/www/" local="130940159560000000" remote="130940159560000000" Dst="0" />
<file name="torrent.gif" server="F:/wamp/www/" local="130940159560000000" remote="130940159560000000" Dst="0" />
<file name="unknown.gif" server="F:/wamp/www/" local="130940159560000000" remote="130940159560000000" Dst="0" />
<file name="zip.gif" server="F:/wamp/www/" local="130940159560000000" remote="130940159560000000" Dst="0" />
</dwsync>